calculator_mcp/__init__.py
calculator_mcp/server.py
calculator_mcp-0.1.4.dist-info/LICENSE
calculator_mcp-0.1.4.dist-info/METADATA
calculator_mcp-0.1.4.dist-info/WHEEL
calculator_mcp-0.1.4.dist-info/entry_points.txt
calculator_mcp-0.1.4.dist-info/RECORD
