Metadata-Version: 2.3
Name: calculator-mcp
Version: 0.1.4
Summary: MCP server that gives you calculator tools
Author: Azam Afridi
Author-email: azamafridi.ai@gmail.com
Requires-Python: >=3.10
Classifier: Programming Language :: Python :: 3
Classifier: Programming Language :: Python :: 3.10
Classifier: Programming Language :: Python :: 3.11
Classifier: Programming Language :: Python :: 3.12
Classifier: Programming Language :: Python :: 3.13
